{
    "status": "ok",
    "totalResults": 6,
    "articles": [
        {
            "source": {
                "id": "cbc-news",
                "name": "CBC News"
            },
            "author": "CBC News",
            "title": "From juggling to cricket: How parents and teachers can help kids kick the pandemic slump | CBC News",
            "description": "Daily physical activity levels for Canadian children and teens dropped significantly during the pandemic, as school itself has become more sedentary. It's time, say experts, to get kids moving again.",
            "url": "http://www.cbc.ca/news/canada/learning-curve-sedentary-kids-1.6460033",
            "urlToImage": "https://i.cbc.ca/1.6478921.1654530893!/fileImage/httpImage/image.jpg_gen/derivatives/16x9_620/learning-curve.jpg",
            "publishedAt": "2022-06-13T08:07:35.6232108Z",
            "content": "Some young learners are struggling to build early reading skills while others stumble over math concepts. Repeated pandemic pivots have left students out of practice with classroom learning, impacted… [+7578 chars]"
        },
        {
            "source": {
                "id": "al-jazeera-english",
                "name": "Al Jazeera English"
            },
            "author": "Annesha Ghosh",
            "title": "A tribute to Mithali Raj, India’s cricketing genius",
            "description": "Former Indian captain has retired from international cricket after a career that spanned nearly 23 years.",
            "url": "http://www.aljazeera.com/sports/2022/6/13/tribute-to-mithali-raj-indias-batting-genius",
            "urlToImage": "https://www.aljazeera.com/wp-content/uploads/2022/06/2017-07-22T124701Z_82759137_RC1E8A857110_RTRMADP_3_CRICKET-WWC-ENG-IND-FINAL.jpg?resize=1200%2C630",
            "publishedAt": "2022-06-13T06:12:51Z",
            "content": "Even before most casual cricket followers got a glimpse of the batting genius that is the bedrock of her stature as an all-time great, Mithali Raj left her imprint on what would turn out to be a brea… [+8871 chars]"
        },
        {
            "source": {
                "id": "google-news-au",
                "name": "Google News (Australia)"
            },
            "author": "Mike Hytner",
            "title": "Cricket great Shane Warne recognised posthumously in Queen’s birthday honours",
            "description": "Warne and retired former world No 1 tennis player Ash Barty become officers of the Order of Australia",
            "url": "https://amp.theguardian.com/sport/2022/jun/12/cricket-great-shane-warne-recognised-posthumously-in-queens-birthday-honours",
            "urlToImage": "https://i.guim.co.uk/img/media/96666fcc57ed127a2b26bcb61dc35fc4ace63057/0_154_4661_2798/master/4661.jpg?width=1200&height=630&quality=85&auto=format&fit=crop&overlay-align=bottom%2Cleft&overlay-width=100p&overlay-base64=L2ltZy9zdGF0aWMvb3ZlcmxheXMvdGctZGVmYXVsdC5wbmc&enable=upscale&s=331c31dd95e37fa8ef7896c0ee305834",
            "publishedAt": "2022-06-12T20:34:00+00:00",
            "content": "Shane Warne has been recognised posthumously in this years Queens birthday honours list, with the cricket great becoming an officer of the Order of Australia.\r\nThe former Test spinner, who died from … [+3393 chars]"
        },
        {
            "source": {
                "id": "bbc-sport",
                "name": "BBC Sport"
            },
            "author": "BBC Sport",
            "title": "Shane Warne memorial - watch & follow updates",
            "description": "Watch live coverage and follow text updates and tributes from the state memorial for Australian cricket legend Shane Warne at the Melbourne Cricket Ground.",
            "url": "http://www.bbc.co.uk/sport/live/cricket/60916236",
            "urlToImage": "https:////m.files.bbci.co.uk/modules/bbc-morph-sport-seo-meta/1.22.0/images/bbc-sport-logo.png",
            "publishedAt": "2022-03-30T08:22:26.498888Z",
            "content": "Former England bowler and BBC cricket presenter Isa Guha, who became a colleague of Warne's in the commentary box: \"It has been a strange few weeks - a lot of shock and then we did our own tribute at… [+396 chars]"
        },
        {
            "source": {
                "id": "espn-cric-info",
                "name": "ESPN Cric Info"
            },
            "author": null,
            "title": "PCB hands Umar Akmal three-year ban from all cricket | ESPNcricinfo.com",
            "description": "Penalty after the batsman pleaded guilty to not reporting corrupt approaches | ESPNcricinfo.com",
            "url": "http://www.espncricinfo.com/story/_/id/29103103/pcb-hands-umar-akmal-three-year-ban-all-cricket",
            "urlToImage": "https://a4.espncdn.com/combiner/i?img=%2Fi%2Fcricket%2Fcricinfo%2F1099495_800x450.jpg",
            "publishedAt": "2020-04-27T11:41:47Z",
            "content": "Umar Akmal's troubled cricket career has hit its biggest roadblock yet, with the PCB handing him a ban from all representative cricket for three years after he pleaded guilty of failing to report det… [+1506 chars]"
        },
        {
            "source": {
                "id": "espn-cric-info",
                "name": "ESPN Cric Info"
            },
            "author": null,
            "title": "What we learned from watching the 1992 World Cup final in full again | ESPNcricinfo.com",
            "description": "Wides, lbw calls, swing - plenty of things were different in white-ball cricket back then | ESPNcricinfo.com",
            "url": "http://www.espncricinfo.com/story/_/id/28970907/learned-watching-1992-world-cup-final-full-again",
            "urlToImage": "https://a4.espncdn.com/combiner/i?img=%2Fi%2Fcricket%2Fcricinfo%2F1219926_1296x729.jpg",
            "publishedAt": "2020-03-30T15:26:05Z",
            "content": "Last week, we at ESPNcricinfo did something we have been thinking of doing for eight years now: pretend-live ball-by-ball commentary for a classic cricket match. We knew the result, yes, but we tried… [+6823 chars]"
        }
    ]
}